README.rst
setup.cfg
setup.py
omvll/__init__.py
omvll/stub.py
omvll.egg-info/PKG-INFO
omvll.egg-info/SOURCES.txt
omvll.egg-info/dependency_links.txt
omvll.egg-info/not-zip-safe
omvll.egg-info/top_level.txt